firebaseloginscreen/__init__.py
firebaseloginscreen/firebaseloginscreen.kv
firebaseloginscreen/firebaseloginscreen.py
firebaseloginscreen/loadingpopup.kv
firebaseloginscreen/signinscreen.kv
firebaseloginscreen/signinscreen.py
firebaseloginscreen/signupscreen.kv
firebaseloginscreen/signupscreen.py
firebaseloginscreen/transparent_image.png
firebaseloginscreen/welcomescreen.kv
firebaseloginscreen/welcomescreen.py
firebaseloginscreen-1.0.10.dist-info/LICENSE
firebaseloginscreen-1.0.10.dist-info/METADATA
firebaseloginscreen-1.0.10.dist-info/WHEEL
firebaseloginscreen-1.0.10.dist-info/entry_points.txt
firebaseloginscreen-1.0.10.dist-info/top_level.txt
firebaseloginscreen-1.0.10.dist-info/RECORD
