Metadata-Version: 2.1
Name: firebaseloginscreen
Version: 1.0.10
Summary: Log in screen for Kivy applications using Google Firebase.
Home-page: https://github.com/Dirk-Sandberg/firebaseloginscreen
Author: Erik Sandberg
Author-email: eriks@sandbergsoftware.com
License: MIT
Platform: UNKNOWN
Classifier: License :: OSI Approved :: MIT License
Classifier: Programming Language :: Python :: 3
Classifier: Programming Language :: Python :: 3.7
Requires-Python: >=3.6
Requires-Dist: kivymd (>=0.104.1)
